pyzup/__init__.py
pyzup/pyzup.py
pyzup-0.1.2.dist-info/licenses/LICENSE
pyzup-0.1.2.dist-info/METADATA
pyzup-0.1.2.dist-info/WHEEL
pyzup-0.1.2.dist-info/top_level.txt
pyzup-0.1.2.dist-info/RECORD
