Metadata-Version: 2.4
Name: pyzup
Version: 0.1.2
Summary: Reusable upload handler for PDFs, DOCX, PPTX, ZIPs
Author: Punit Tripathi, Mohd. Amir
Author-email: tripathi.punit@proton.me, amir.zilli@gmail.com
License: MIT
Requires-Python: >=3.7
License-File: LICENSE
Requires-Dist: Werkzeug==3.1.3
Requires-Dist: loguru==0.7.3
Dynamic: author
Dynamic: author-email
Dynamic: description
Dynamic: description-content-type
Dynamic: license
Dynamic: license-file
Dynamic: requires-dist
Dynamic: requires-python
Dynamic: summary
